calculator/__init__.py
calculator/calc.py
calculator/unit_tests.py
olgamrl_project_p1-1.0.data/scripts/calc.py
olgamrl_project_p1-1.0.dist-info/METADATA
olgamrl_project_p1-1.0.dist-info/WHEEL
olgamrl_project_p1-1.0.dist-info/top_level.txt
olgamrl_project_p1-1.0.dist-info/RECORD
