Metadata-Version: 2.1
Name: olgamrl-project-p1
Version: 1.0
Summary: A small example package
Home-page: https://github.com/naturalett/getting-started
Author: Foo Bar
Author-email: lidor.ettinger@example.com
License: UNKNOWN
Platform: UNKNOWN
Requires-Python: >=3.9
Requires-Dist: distribution-Final
